Workbook
Name aporte: '% INVEST'!$C$21
Name quantidade_de_anos: '% INVEST'!$C$22
Name rendimento_carteira: '% INVEST'!$G$23
Name rendimento_mensal: '% INVEST'!$C$23
Name salario_mensal: '% INVEST'!$G$21
Name sugestao_de_investimento: '% INVEST'!$G$25

Sheet % INVEST
B19: INVESTIMENTO MENSAL | F19: CONFIGURAÇOES
B21: QUANTO INVESTIR POR MÊS | C21: 540 | F21: SEU SALÁRIO MENSAL | G21: 1800
B22: POR QUANTOS ANOS? | C22: 5
B23: TAXA DE RENDIMENTO MENSAL? | C23: 0.01079 | F23: RENDIMENTO CARTEIRA | G23: 0.0089
B24: QUANTO DE PATRIMONIO ACUMULADO TEREI? | C24: =FV(rendimento_mensal,quantidade_de_anos*12,C21*-1) -> 45239.534
B25: QUANTO DE DIVIDENDO POR MÊS? | C25: =C24*rendimento_mensal -> 488.13457 | F25: SUGESTAO DE INVESTIMENTO | G25: =G21*30% -> 540
B30: CENÁRIOS | C30: TOTAL | D30: MENSAL
B31: QUANTO EM 1 ANO? | C31: =FV($C$23,1*12,$C$21*-1) -> 6878.7284 | D31: =C31*rendimento_carteira -> 61.220683
B32: QUANTO EM 10 ANOS? | C32: =FV($C$23,10*12,$C$21*-1) -> 131373.47 | D32: =C32*rendimento_carteira -> 1169.2239
B33: QUANTO EM 20 ANOS? | C33: =FV($C$23,20*12,$C$21*-1) -> 607607.14 | D33: =C33*rendimento_carteira -> 5407.7035
B36: PERFIL | C36: MODERADO
B37: VALOR INVESTIDO POR MÊS | C37: 540
B40: TIPO DE FUNDO IMOBILIÁRIO (FII) | C40: % SUGERIDO | D40: VALORES
B41: PAPEL | C41: =VLOOKUP($C$36&"-"&B41,'FII - PERFIS'!$B:$E,4,) -> 0.32 | D41: =C41*$C$37 -> 172.8
B42: TIJOLO | C42: =VLOOKUP($C$36&"-"&B42,'FII - PERFIS'!$B:$E,4,) -> 0.35 | D42: =C42*$C$37 -> 189
B43: HÍBRIDOS | C43: =VLOOKUP($C$36&"-"&B43,'FII - PERFIS'!$B:$E,4,) -> 0.08 | D43: =C43*$C$37 -> 43.2
B44: FOFs | C44: =VLOOKUP($C$36&"-"&B44,'FII - PERFIS'!$B:$E,4,) -> 0.05 | D44: =C44*$C$37 -> 27
B45: DESENVOLVIMENTO | C45: =VLOOKUP($C$36&"-"&B45,'FII - PERFIS'!$B:$E,4,) -> 0.1 | D45: =C45*$C$37 -> 54
B46: HOTELARIA | C46: =VLOOKUP($C$36&"-"&B46,'FII - PERFIS'!$B:$E,4,) -> 0.1 | D46: =C46*$C$37 -> 54
D47: =SUM(D41:D46) -> 540

Sheet FII - PERFIS
B3: CHAVE ÚNICA | C3: PERFIL | D3: TIPOS DE FII | E3: % PERCENTUAL | H3: MODERADO-TIJOLO | I3: =VLOOKUP(H3,$B:$E,4,FALSE) -> 0.35
B4: =$C$4&"-"&D4 -> CONSERVADOR-PAPEL | C4: CONSERVADOR | D4: PAPEL | E4: 0.3
B5: =$C$4&"-"&D5 -> CONSERVADOR-TIJOLO | C5: CONSERVADOR | D5: TIJOLO | E5: 0.5
B6: =$C$4&"-"&D6 -> CONSERVADOR-HÍBRIDOS | C6: CONSERVADOR | D6: HÍBRIDOS | E6: 0.1
B7: =$C$4&"-"&D7 -> CONSERVADOR-FOFs | C7: CONSERVADOR | D7: FOFs | E7: 0.1
B8: =$C$4&"-"&D8 -> CONSERVADOR-DESENVOLVIMENTO | C8: CONSERVADOR | D8: DESENVOLVIMENTO | E8: 0
B9: =$C$4&"-"&D9 -> CONSERVADOR-HOTELARIA | C9: CONSERVADOR | D9: HOTELARIA | E9: 0
B10: =$C$10&"-"&D10 -> MODERADO-PAPEL | C10: MODERADO | D10: PAPEL | E10: 0.32
B11: MODERADO-TIJOLO | C11: MODERADO | D11: TIJOLO | E11: 0.35
B12: =$C$10&"-"&D12 -> MODERADO-HÍBRIDOS | C12: MODERADO | D12: HÍBRIDOS | E12: 0.08
B13: =$C$10&"-"&D13 -> MODERADO-FOFs | C13: MODERADO | D13: FOFs | E13: 0.05
B14: =$C$10&"-"&D14 -> MODERADO-DESENVOLVIMENTO | C14: MODERADO | D14: DESENVOLVIMENTO | E14: 0.1
B15: =$C$10&"-"&D15 -> MODERADO-HOTELARIA | C15: MODERADO | D15: HOTELARIA | E15: 0.1
B16: =$C$16&"-"&D16 -> AGRESSIVO-PAPEL | C16: AGRESSIVO | D16: PAPEL | E16: 0.5
B17: =$C$16&"-"&D17 -> AGRESSIVO-TIJOLO | C17: AGRESSIVO | D17: TIJOLO | E17: 0.1
B18: =$C$16&"-"&D18 -> AGRESSIVO-HÍBRIDOS | C18: AGRESSIVO | D18: HÍBRIDOS | E18: 0.05
B19: =$C$16&"-"&D19 -> AGRESSIVO-FOFs | C19: AGRESSIVO | D19: FOFs | E19: 0.55
B20: =$C$16&"-"&D20 -> AGRESSIVO-DESENVOLVIMENTO | C20: AGRESSIVO | D20: DESENVOLVIMENTO | E20: 0.2
B21: =$C$16&"-"&D21 -> AGRESSIVO-HOTELARIA | C21: AGRESSIVO | D21: HOTELARIA | E21: 0.1
